rtl/thing.v
`timescale 1ns/1ps

module thing (
    input clk,
    input reset,
    output reg done,
    output reg [7:0] letter
);

localparam int STRING = 12;
reg [3:0] i;
wire [7:0] foo [0:STRING];

assign foo[0]  = 8'h48; // 'H'
assign foo[1]  = 8'h65; // 'e'
assign foo[2]  = 8'h6C; // 'l'
assign foo[3]  = 8'h6C; // 'l'
assign foo[4]  = 8'h6F; // 'o'
assign foo[5]  = 8'h2C; // ','
assign foo[6]  = 8'h20; // ' '
assign foo[7]  = 8'h57; // 'W'
assign foo[8]  = 8'h6F; // 'o'
assign foo[9]  = 8'h72; // 'r'
assign foo[10] = 8'h6C; // 'l'
assign foo[11] = 8'h64; // 'd'
assign foo[12] = 8'h21; // '!'

initial begin
    i = 0;
end

always @ (posedge clk or posedge reset) begin
    if (reset) begin
        i <= 0;
        letter <= 8'h00;
    end else if (i <= STRING) begin
        letter <= foo[i];
        i <= i + 1;
    end else if (letter == 8'h21) begin
        done = 1;
    end
end

endmodule

tb/thingTest.v
`timescale 1ns/1ps

module thingTest;

reg clk;
reg reset;
wire done;
wire [7:0] letter;

    thing dut (
        .clk(clk),
        .reset(reset),
        .letter(letter),
        .done(done)
    );

always #5 clk = ~clk;

initial begin
    // set starting values
    clk = 0;
    reset = 1;

    $dumpfile("thingDump.vcd");
    $dumpvars(0, thing);

    // start the timulation
    #20 reset = 0;

    repeat (13) begin
        #10 $display("Time: %0tps, Letter: %s", $time, letter);
    end

    #200 $finish;
end

always @(posedge clk) begin
    if (done) begin
        reset <= 1;
    end
end

endmodule

sim/waveforms/thingDump.vcd
$version Generated by VerilatedVcd $end
$timescale 1ps $end
 $scope module TOP $end
  $scope module thingTest $end
   $var wire 1 0 clk $end
   $var wire 1 1 reset $end
   $var wire 1 2 done $end
   $var wire 8 3 letter [7:0] $end
   $scope module dut $end
    $var wire 1 0 clk $end
    $var wire 1 1 reset $end
    $var wire 1 2 done $end
    $var wire 8 3 letter [7:0] $end
    $var wire 32 5 STRING [31:0] $end
    $var wire 4 4 i [3:0] $end
    $var wire 8 # foo[0] [7:0] $end
    $var wire 8 $ foo[1] [7:0] $end
    $var wire 8 % foo[2] [7:0] $end
    $var wire 8 & foo[3] [7:0] $end
    $var wire 8 ' foo[4] [7:0] $end
    $var wire 8 ( foo[5] [7:0] $end
    $var wire 8 ) foo[6] [7:0] $end
    $var wire 8 * foo[7] [7:0] $end
    $var wire 8 + foo[8] [7:0] $end
    $var wire 8 , foo[9] [7:0] $end
    $var wire 8 - foo[10] [7:0] $end
    $var wire 8 . foo[11] [7:0] $end
    $var wire 8 / foo[12] [7:0] $end
   $upscope $end
  $upscope $end
 $upscope $end
$enddefinitions $end


#0
b01001000 #
b01100101 $
b01101100 %
b01101100 &
b01101111 '
b00101100 (
b00100000 )
b01010111 *
b01101111 +
b01110010 ,
b01101100 -
b01100100 .
b00100001 /
00
11
02
b00000000 3
b0000 4
b00000000000000000000000000001100 5
#5000
10
#10000
00
#15000
10
#20000
00
01
#25000
10
b01001000 3
b0001 4
#30000
00
#35000
10
b01100101 3
b0010 4
#40000
00
#45000
10
b01101100 3
b0011 4
#50000
00
#55000
10
b0100 4
#60000
00
#65000
10
b01101111 3
b0101 4
#70000
00
#75000
10
b00101100 3
b0110 4
#80000
00
#85000
10
b00100000 3
b0111 4
#90000
00
#95000
10
b01010111 3
b1000 4
#100000
00
#105000
10
b01101111 3
b1001 4
#110000
00
#115000
10
b01110010 3
b1010 4
#120000
00
#125000
10
b01101100 3
b1011 4
#130000
00
#135000
10
b01100100 3
b1100 4
#140000
00
#145000
10
b00100001 3
b1101 4
#150000
00
#155000
10
11
12
b00000000 3
b0000 4
